dicergirl/plugins/scp/__init__.py
dicergirl/plugins/scp/agent.py
dicergirl/plugins/scp/attributes.py
dicergirl/plugins/scp/backend.py
dicergirl/plugins/scp/cards.py
dicergirl/plugins/scp/docimasy.py
dicergirl/plugins/scp/nbhandlers.py
dicergirl/plugins/scp/scpcards.py
dicergirl/plugins/scp/scputils.py
dicergirl/scp/__init__.py
dicergirl/scp/agent.py
dicergirl/scp/attributes.py
dicergirl/scp/nbhandlers.py
dicergirl/scp/scpcards.py
dicergirl/scp/scputils.py
dicergirl_plugin_scp-2.0.0.dist-info/METADATA
dicergirl_plugin_scp-2.0.0.dist-info/WHEEL
dicergirl_plugin_scp-2.0.0.dist-info/top_level.txt
dicergirl_plugin_scp-2.0.0.dist-info/RECORD
