Metadata-Version: 2.1
Name: dicergirl-plugin-scp
Version: 2.0.0
Summary: Dicergirl SCP 模式插件
Home-page: https://gitee.com/unvisitor/dicergirl-plugin-scp/
Author: Night Resurgent <fu050409@163.com>
Author-email: fu050409@163.com
License: Apache-2.0
Project-URL: Bug Tracker, https://gitee.com/unvisitor/dicergirl-plugin-scp/issues
Classifier: Programming Language :: Python :: 3
Classifier: License :: OSI Approved :: Apache Software License
Classifier: Operating System :: OS Independent
Requires-Python: >=3
Requires-Dist: dicergirl
